fhir_parser/__init__.py
fhir_parser/fhir.py
fhir_parser/observation.py
fhir_parser/parser.py
fhir_parser/patient.py
FHIR_Parser-0.1.5.dist-info/LICENSE
FHIR_Parser-0.1.5.dist-info/METADATA
FHIR_Parser-0.1.5.dist-info/WHEEL
FHIR_Parser-0.1.5.dist-info/top_level.txt
FHIR_Parser-0.1.5.dist-info/RECORD
