Metadata-Version: 2.1
Name: FHIR-Parser
Version: 0.1.5
Summary: An elegant and simple FHIR library for Python, built for human beings
Home-page: https://github.com/greenfrogs/FHIR-Parser
Author: Greenfrogs
Author-email: 5961364+greenfrogs@users.noreply.github.com
License: Apache License 2.0
Platform: UNKNOWN
Classifier: Programming Language :: Python :: 3
Classifier: Intended Audience :: Developers
Classifier: Operating System :: OS Independent
Requires-Python: >=3.7
Requires-Dist: requests (>=2.23.0)
Requires-Dist: python-dateutil (>=2.8.1)
